oaas_sdk_py/__init__.py
oaas_sdk_py/model.py
oaas_sdk_py-0.3.3.dist-info/LICENSE
oaas_sdk_py-0.3.3.dist-info/METADATA
oaas_sdk_py-0.3.3.dist-info/WHEEL
oaas_sdk_py-0.3.3.dist-info/top_level.txt
oaas_sdk_py-0.3.3.dist-info/RECORD
